lazy_socket/__init__.py
lazy_socket/client.py
lazy_socket/server.py
lazy_socket-0.0.6.dist-info/licenses/LICENSE
lazy_socket-0.0.6.dist-info/METADATA
lazy_socket-0.0.6.dist-info/WHEEL
lazy_socket-0.0.6.dist-info/top_level.txt
lazy_socket-0.0.6.dist-info/RECORD
