Metadata-Version: 2.4
Name: lazy-socket
Version: 0.0.6
Summary: A lightweight WebSocket-based communication library
Author-email: KyleTheScientist <kylethescientist@gmail.com>
Classifier: Programming Language :: Python :: 3.10
Classifier: Programming Language :: Python :: 3.11
Classifier: Programming Language :: Python :: 3.12
Classifier: Programming Language :: Python :: 3.13
Classifier: License :: OSI Approved :: MIT License
Classifier: Operating System :: OS Independent
License-File: LICENSE
Requires-Dist: websockets==15.0.1
Requires-Dist: zeroconf==0.148.0
Dynamic: license-file
